ptwidget/__init__.py
ptwidget/pivottable.py
ptwidget-0.1.0.dist-info/LICENSE
ptwidget-0.1.0.dist-info/METADATA
ptwidget-0.1.0.dist-info/WHEEL
ptwidget-0.1.0.dist-info/top_level.txt
ptwidget-0.1.0.dist-info/RECORD
