Metadata-Version: 2.1
Name: ptwidget
Version: 0.1.0
Summary: Pivot Table Widget
Home-page: https://github.com/hemantbaxi/PivotTable-Widget
Author: Hemant Baxi
Author-email: baxihemant@gmail.com
License: UNKNOWN
Project-URL: Bug Tracker, https://github.com/hemantbaxi/PivotTable-Widget/issues
Platform: UNKNOWN
Classifier: Programming Language :: Python :: 3
Classifier: License :: OSI Approved :: MIT License
Classifier: Operating System :: OS Independent
Requires-Python: >=3.8
License-File: LICENSE
Requires-Dist: pivottablejs
Requires-Dist: ipyiframe
Requires-Dist: ipywidgets
Requires-Dist: pandas
